riot/__init__.py
riot/connection.py
riot/api/account.py
riot/api/lol/__init__.py
riot/api/lol/league.py
riot/api/lol/spectator.py
riot/api/lol/summoner.py
riot/api/tft/__init__.py
riot/api/tft/league.py
riot/constants/__init__.py
riot/constants/champions.py
riot/constants/game_mods.py
riot/constants/game_types.py
riot/constants/regions.py
riot/constants/service_proxies.py
python_riot-0.3.1.dist-info/METADATA
python_riot-0.3.1.dist-info/WHEEL
python_riot-0.3.1.dist-info/licenses/LICENSE
python_riot-0.3.1.dist-info/RECORD
