Metadata-Version: 2.3
Name: python_riot
Version: 0.3.1
Summary: Inoffical python lib for the Riot API written in python
Author-email: Johannes Eimer <info@jep-dev.com>
License-Expression: MIT
License-File: LICENSE
Keywords: API,League of Legends,Python,Riot
Requires-Python: >=3.11
